README.rst
setup.py
./contactpp/__init__.py
./contactpp/outputs.py
./contactpp/solve.py
./contactpp/swell.py
./contactpp/troullier.py
./contactpp/utp.py
bin/gen_pseudo
bin/gen_pseudo_swell
bin/gen_pseudo_troullier
bin/gen_pseudo_utp
contactpp.egg-info/PKG-INFO
contactpp.egg-info/SOURCES.txt
contactpp.egg-info/dependency_links.txt
contactpp.egg-info/not-zip-safe
contactpp.egg-info/top_level.txt