Metadata-Version: 1.1
Name: contactpp
Version: 1.1
Summary: Pseudopotential generator for the contact interaction
Home-page: https://pypi.python.org/pypi/contactpp
Author: Pascal Bugnion
Author-email: pascal@bugnion.org
License: new BSD
Platform: UNKNOWN
Classifier: Intended Audience :: Science/Research
Classifier: Intended Audience :: Developers
Classifier: License :: OSI Approved :: BSD License
Classifier: Programming Language :: Python
Classifier: Topic :: Software Development
Classifier: Topic :: Scientific/Engineering
Classifier: Operating System :: POSIX
Classifier: Operating System :: Unix
Classifier: Operating System :: MacOS
Classifier: Programming Language :: Python :: 2
Classifier: Programming Language :: Python :: 2.7
